{
  "version": "7",
  "dialect": "postgresql",
  "entries": [
    {
      "idx": 0,
      "version": "7",
      "when": 1774463456936,
      "tag": "0000_complete_loners",
      "breakpoints": true
    },
    {
      "idx": 1,
      "version": "7",
      "when": 1774474788488,
      "tag": "0001_funny_wildside",
      "breakpoints": true
    },
    {
      "idx": 2,
      "version": "7",
      "when": 1774488267893,
      "tag": "0002_ordinary_black_widow",
      "breakpoints": true
    },
    {
      "idx": 3,
      "version": "7",
      "when": 1774490845502,
      "tag": "0003_short_shocker",
      "breakpoints": true
    }
  ]
}